src/__init__.py
src/config.py
src/main.py
src/sentry.py
src/commands/__init__.py
src/commands/ai.py
src/conversation/__init__.py
src/conversation/manager.py
src/conversation/persistence.py
src/conversation/types.py
src/mcp_client/__init__.py
src/mcp_client/client.py
src/mcp_client/types.py
webex_bot_ai-0.2.0.dist-info/METADATA
webex_bot_ai-0.2.0.dist-info/WHEEL
webex_bot_ai-0.2.0.dist-info/entry_points.txt
webex_bot_ai-0.2.0.dist-info/licenses/LICENSE
webex_bot_ai-0.2.0.dist-info/RECORD
