Metadata-Version: 2.4
Name: webex-bot-ai
Version: 0.2.0
Summary: AI Bot for Webex with thread context and MCP support
Project-URL: Homepage, https://github.com/mhajder/webex-bot-ai
Project-URL: Repository, https://github.com/mhajder/webex-bot-ai
Project-URL: Documentation, https://github.com/mhajder/webex-bot-ai#readme
Project-URL: Issues, https://github.com/mhajder/webex-bot-ai/issues
Author: Mateusz Hajder
License: MIT
License-File: LICENSE
Keywords: ai,ai-assistant,automation,bot,chatbot,fastmcp,litellm,mcp,webex,webex-teams
Classifier: Development Status :: 3 - Alpha
Classifier: Framework :: AsyncIO
Classifier: Intended Audience :: Developers
Classifier: License :: OSI Approved :: MIT License
Classifier: Operating System :: OS Independent
Classifier: Programming Language :: Python :: 3
Classifier: Programming Language :: Python :: 3 :: Only
Classifier: Programming Language :: Python :: 3.11
Classifier: Programming Language :: Python :: 3.12
Classifier: Programming Language :: Python :: 3.13
Classifier: Topic :: Communications :: Chat
Requires-Python: <3.14,>=3.11
Requires-Dist: aiosqlite>=0.20.0
Requires-Dist: fastmcp>=2.3.0
Requires-Dist: litellm>=1.40.0
Requires-Dist: pydantic-settings>=2.0.0
Requires-Dist: pydantic>=2.0.0
Requires-Dist: python-dotenv>=1.0.0
Requires-Dist: webex-bot>=1.0.8
Provides-Extra: sentry
Requires-Dist: sentry-sdk[litellm]>=2.43.0; extra == 'sentry'
